{
  "$schema": "https://raw.githubusercontent.com/electron-userland/electron-builder/master/packages/app-builder-lib/scheme.json",
  "appId": "YourAppID",
  "asar": true,
  "productName": "Gml-Desktop",
  "directories": {
    "output": "release/${version}"
  },
  "files": [
    "dist",
    "dist-electron"
  ],
  "mac": {
    "target": [
      "dmg"
    ],
    "artifactName": "${productName}-Mac-${version}-Installer.${ext}",
    "icon": "src/assets/logo.icon" // Adicione o caminho do ícone aqui
  },
  "win": {
    "target": [
      {
        "target": "nsis",
        "arch": [
          "x64"
        ]
      }
    ],
    "artifactName": "${productName}-Windows-${version}-Setup.${ext}",
    "icon": "src/assets/logo.icon" // Adicione o caminho do ícone aqui
  },
  "nsis": {
    "oneClick": false,
    "perMachine": false,
    "allowToChangeInstallationDirectory": true,
    "deleteAppDataOnUninstall": false
  },
  "linux": {
    "target": [
      "AppImage"
    ],
    "artifactName": "${productName}-Linux-${version}.${ext}",
    "icon": "src/assets/logo.icon" // Adicione o caminho do ícone aqui
  }
}
